ez_compare/__init__.py
ez_compare/core.py
ez_compare/example.py
ez_compare-0.2.dist-info/METADATA
ez_compare-0.2.dist-info/WHEEL
ez_compare-0.2.dist-info/top_level.txt
ez_compare-0.2.dist-info/RECORD
