Metadata-Version: 2.1
Name: ez-compare
Version: 0.2
Summary: Easily to compare two text
Home-page: https://github.com/cnkailyn/ez_compare
Author: kailyn
Author-email: cnkailyn@gmail.com
License: UNKNOWN
Platform: UNKNOWN
Requires-Dist: diff-match-patch (==20200713)
